easyams/__init__.py
easyams/img_loader.py
easyams/py.typed
easyams/stag_gcp.py
easyams/ui.py
easyams/updator.py
easyams/utils.py
easyams/video_split.py
easyams/resources/__init__.py
easyams/resources/lab_logo.png
easyams/sahi_onnx/LICENSE
easyams/sahi_onnx/__init__.py
easyams/sahi_onnx/annotation.py
easyams/sahi_onnx/auto_model.py
easyams/sahi_onnx/predict.py
easyams/sahi_onnx/prediction.py
easyams/sahi_onnx/slicing.py
easyams/sahi_onnx/models/__init__.py
easyams/sahi_onnx/models/base.py
easyams/sahi_onnx/models/yolov8onnx.py
easyams/sahi_onnx/postprocess/__init__.py
easyams/sahi_onnx/postprocess/combine.py
easyams/sahi_onnx/postprocess/utils.py
easyams/sahi_onnx/postprocess/legacy/__init__.py
easyams/sahi_onnx/postprocess/legacy/combine.py
easyams/sahi_onnx/scripts/__init__.py
easyams/sahi_onnx/scripts/coco2fiftyone.py
easyams/sahi_onnx/scripts/coco2yolov5.py
easyams/sahi_onnx/scripts/coco_error_analysis.py
easyams/sahi_onnx/scripts/coco_evaluation.py
easyams/sahi_onnx/scripts/predict.py
easyams/sahi_onnx/scripts/predict_fiftyone.py
easyams/sahi_onnx/scripts/slice_coco.py
easyams/sahi_onnx/utils/__init__.py
easyams/sahi_onnx/utils/coco.py
easyams/sahi_onnx/utils/compatibility.py
easyams/sahi_onnx/utils/cv.py
easyams/sahi_onnx/utils/file.py
easyams/sahi_onnx/utils/import_utils.py
easyams/sahi_onnx/utils/shapely.py
easyams/sahi_onnx/utils/sparseyolov5.py
easyams/sahi_onnx/utils/versions.py
easyams/sahi_onnx/utils/yolov8onnx.py
easyams/web_api/__init__.py
easyams/web_api/conf.py
easyams/web_api/data.py
easyams/web_api/pdf.py
easyams/web_api/sphinx.py
easyams-0.1.6.dist-info/METADATA
easyams-0.1.6.dist-info/WHEEL
easyams-0.1.6.dist-info/licenses/LICENSE
easyams-0.1.6.dist-info/RECORD
