Metadata-Version: 2.4
Name: easyams
Version: 0.1.6
Summary: Easy Agisoft MetaShape (EasyAMS) Plugin with extended functions for smart agriculture.
Project-URL: Homepage, https://github.com/UTokyo-FieldPhenomics-Lab/EasyAMS
Project-URL: Issues, https://github.com/UTokyo-FieldPhenomics-Lab/EasyAMS/issues
Author-email: Haozhou Wang <howcanoewang@gmail.com>
License: MIT
License-File: LICENSE
Classifier: Development Status :: 3 - Alpha
Classifier: Intended Audience :: Science/Research
Classifier: Operating System :: OS Independent
Classifier: Programming Language :: Python :: 3
Classifier: Programming Language :: Python :: 3 :: Only
Classifier: Programming Language :: Python :: 3.8
Classifier: Programming Language :: Python :: 3.9
Classifier: Programming Language :: Python :: 3.10
Classifier: Programming Language :: Python :: 3.11
Classifier: Programming Language :: Python :: 3.12
Classifier: Topic :: Scientific/Engineering :: Artificial Intelligence
Classifier: Topic :: Scientific/Engineering :: GIS
Classifier: Topic :: Scientific/Engineering :: Image Processing
Requires-Python: >=3.9.13
Requires-Dist: furo>=2024.8.6
Requires-Dist: numpy==1.26.4
Requires-Dist: onnx==1.17.0
Requires-Dist: onnxruntime==1.19.2
Requires-Dist: opencv-python==4.10.0.84
Requires-Dist: pillow>=8.2.0
Requires-Dist: pybboxes>=0.1.6
Requires-Dist: pymupdf>=1.26.3
Requires-Dist: requests>=2.32.3
Requires-Dist: shapely>=2.0.0
Requires-Dist: sphinx>=7.4.7
Requires-Dist: stag-python>=1.1.0
Requires-Dist: tqdm>=4.67.1
